medical_shape_building/__init__.py
medical_shape_building/dicom_dataset.py
medical_shape_building/logging_tqdm.py
medical_shape_building/pca.py
medical_shape_building/postprocessing.py
medical_shape_building/process_dataset.py
medical_shape_building/process_subject.py
medical_shape_building/procrustes.py
medical_shape_building/registration_pipeline.py
medical_shape_building/split_structures.py
medical_shape_building/transfer_landmarks.py
medical_shape_building/utils.py
medical_shape_building/visualize.py
medical_shape_building/airlab/__init__.py
medical_shape_building/airlab/affine.py
medical_shape_building/airlab/affine_demons.py
medical_shape_building/airlab/demons.py
medical_shape_building/airlab/image.py
medical_shape_building/airlab/loss.py
medical_shape_building/airlab/points.py
medical_shape_building/airlab/registration.py
medical_shape_building/airlab/regulariser.py
medical_shape_building/airlab/transformation.py
medical_shape_building/airlab/utils.py
medical_shape_building/entrypoints/__init__.py
medical_shape_building/entrypoints/get_parser.py
medical_shape_building/entrypoints/subcommands.py
medical_shape_building/sampling/__init__.py
medical_shape_building/sampling/sampler.py
medical_shape_building/sampling/strategy/__init__.py
medical_shape_building/sampling/strategy/base.py
medical_shape_building/sampling/strategy/kmeans.py
medical_shape_building/sampling/strategy/manual.py
medical_shape_building/sampling/strategy/random.py
medical_shape_building/sampling/strategy/semi_manual.py
medical_shape_building/snapping/__init__.py
medical_shape_building/snapping/snapper.py
medical_shape_building/snapping/strategy/__init__.py
medical_shape_building/snapping/strategy/base.py
medical_shape_building/snapping/strategy/distance.py
medical_shape_building/snapping/strategy/identity.py
medical_shape_building/snapping/strategy/local_normal.py
medical_shape_building/snapping/strategy/normal.py
medical_shape_building-0.0.4.dist-info/METADATA
medical_shape_building-0.0.4.dist-info/WHEEL
medical_shape_building-0.0.4.dist-info/top_level.txt
medical_shape_building-0.0.4.dist-info/RECORD
