Metadata-Version: 2.1
Name: medical-shape-building
Version: 0.0.4
Summary: This is a super duper package
Home-page: https://github.com/justusschock/medical-shape-building
Author: Justus Schock
Author-email: justus.schock@posteo.de
License: UNKNOWN
Project-URL: source, https://github.com/justusschock/medical-shape-building
Project-URL: tracker, https://github.com/justusschock/medical-shape-building/issues
Keywords: deep learning,machine learning,pytorch,medical,AI
Platform: UNKNOWN
Classifier: Programming Language :: Python :: 3
Requires-Python: >=3.7
Requires-Dist: torch (>=1.7)
Requires-Dist: pytorch-lightning (>=1.5)
Requires-Dist: rising (>=0.2.1)
Requires-Dist: scikit-image (>=0.18)
Requires-Dist: torchio (>=0.18.71)
Requires-Dist: medical-dl-utils (>=0.0.2)
Requires-Dist: medical-shape (>=0.0.5)
Requires-Dist: sklearn
Requires-Dist: tqdm
